odoo9_addon_web_shortcut-9.0.1.0.0.99.dev17-py2.7-nspkg.pth
odoo9_addon_web_shortcut-9.0.1.0.0.99.dev17.dist-info/DESCRIPTION.rst
odoo9_addon_web_shortcut-9.0.1.0.0.99.dev17.dist-info/METADATA
odoo9_addon_web_shortcut-9.0.1.0.0.99.dev17.dist-info/RECORD
odoo9_addon_web_shortcut-9.0.1.0.0.99.dev17.dist-info/WHEEL
odoo9_addon_web_shortcut-9.0.1.0.0.99.dev17.dist-info/metadata.json
odoo9_addon_web_shortcut-9.0.1.0.0.99.dev17.dist-info/namespace_packages.txt
odoo9_addon_web_shortcut-9.0.1.0.0.99.dev17.dist-info/top_level.txt
odoo_addons/web_shortcut/LICENSE
odoo_addons/web_shortcut/README.rst
odoo_addons/web_shortcut/__init__.py
odoo_addons/web_shortcut/__openerp__.py
odoo_addons/web_shortcut/i18n/ar.po
odoo_addons/web_shortcut/i18n/bs.po
odoo_addons/web_shortcut/i18n/ca.po
odoo_addons/web_shortcut/i18n/cs.po
odoo_addons/web_shortcut/i18n/da.po
odoo_addons/web_shortcut/i18n/de.po
odoo_addons/web_shortcut/i18n/el.po
odoo_addons/web_shortcut/i18n/en_GB.po
odoo_addons/web_shortcut/i18n/es.po
odoo_addons/web_shortcut/i18n/fi.po
odoo_addons/web_shortcut/i18n/fr.po
odoo_addons/web_shortcut/i18n/gl.po
odoo_addons/web_shortcut/i18n/hr.po
odoo_addons/web_shortcut/i18n/hu.po
odoo_addons/web_shortcut/i18n/it.po
odoo_addons/web_shortcut/i18n/lt.po
odoo_addons/web_shortcut/i18n/mk.po
odoo_addons/web_shortcut/i18n/mn.po
odoo_addons/web_shortcut/i18n/nl.po
odoo_addons/web_shortcut/i18n/pl.po
odoo_addons/web_shortcut/i18n/pt.po
odoo_addons/web_shortcut/i18n/pt_BR.po
odoo_addons/web_shortcut/i18n/ro.po
odoo_addons/web_shortcut/i18n/ru.po
odoo_addons/web_shortcut/i18n/sl.po
odoo_addons/web_shortcut/i18n/sv.po
odoo_addons/web_shortcut/i18n/th.po
odoo_addons/web_shortcut/i18n/tr.po
odoo_addons/web_shortcut/i18n/vi.po
odoo_addons/web_shortcut/i18n/zh_CN.po
odoo_addons/web_shortcut/i18n/zh_TW.po
odoo_addons/web_shortcut/models/__init__.py
odoo_addons/web_shortcut/models/ir_ui_menu.py
odoo_addons/web_shortcut/models/web_shortcut.py
odoo_addons/web_shortcut/security/ir.model.access.csv
odoo_addons/web_shortcut/static/description/icon.png
odoo_addons/web_shortcut/static/src/css/web_shortcut.css
odoo_addons/web_shortcut/static/src/js/web_shortcut.js
odoo_addons/web_shortcut/static/src/xml/web_shortcut.xml
odoo_addons/web_shortcut/templates/assets.xml
odoo_addons/web_shortcut/tests/__init__.py
odoo_addons/web_shortcut/tests/test_web_shortcut.py
